superagent_ai/__init__.py
superagent_ai/client.py
superagent_ai/py.typed
superagent_guard/__init__.py
superagent_guard/py.typed
superagent_ai-0.0.23.dist-info/METADATA
superagent_ai-0.0.23.dist-info/WHEEL
superagent_ai-0.0.23.dist-info/top_level.txt
superagent_ai-0.0.23.dist-info/RECORD
