Metadata-Version: 2.4
Name: superagent-ai
Version: 0.0.23
Summary: Python SDK for Superagent.
Author: Superagent
License-Expression: MIT
Keywords: superagent,guard,sdk,safety
Classifier: Programming Language :: Python :: 3
Classifier: Programming Language :: Python :: 3.9
Classifier: Programming Language :: Python :: 3.10
Classifier: Programming Language :: Python :: 3.11
Classifier: Programming Language :: Python :: 3.12
Requires-Python: >=3.9
Requires-Dist: httpx<1.0.0,>=0.25
Provides-Extra: tests
Requires-Dist: pytest>=7.4; extra == "tests"
Requires-Dist: pytest-asyncio>=0.23; extra == "tests"
Requires-Dist: python-dotenv>=1.0; extra == "tests"
